[
  {
    "date": "2016-01-01",
    "year": 2016,
    "month": 1,
    "unemployed_15_24": 283.6,
    "unemployment_rate_15_24": 10.7,
    "unemployed_15_30": 402.8,
    "unemployment_rate_15_30": 6.9
  },
  {
    "date": "2016-02-01",
    "year": 2016,
    "month": 2,
    "unemployed_15_24": 236.1,
    "unemployment_rate_15_24": 9,
    "unemployed_15_30": 340.6,
    "unemployment_rate_15_30": 5.7
  },
  {
    "date": "2016-03-01",
    "year": 2016,
    "month": 3,
    "unemployed_15_24": 285,
    "unemployment_rate_15_24": 10.9,
    "unemployed_15_30": 416.1,
    "unemployment_rate_15_30": 7
  },
  {
    "date": "2016-04-01",
    "year": 2016,
    "month": 4,
    "unemployed_15_24": 305.6,
    "unemployment_rate_15_24": 11.5,
    "unemployed_15_30": 405.7,
    "unemployment_rate_15_30": 6.9
  },
  {
    "date": "2016-05-01",
    "year": 2016,
    "month": 5,
    "unemployed_15_24": 291.6,
    "unemployment_rate_15_24": 11.1,
    "unemployed_15_30": 395.2,
    "unemployment_rate_15_30": 6.8
  },
  {
    "date": "2016-06-01",
    "year": 2016,
    "month": 6,
    "unemployed_15_24": 240.5,
    "unemployment_rate_15_24": 9.6,
    "unemployed_15_30": 387.3,
    "unemployment_rate_15_30": 6.6
  },
  {
    "date": "2016-07-01",
    "year": 2016,
    "month": 7,
    "unemployed_15_24": 309,
    "unemployment_rate_15_24": 11.8,
    "unemployed_15_30": 446.9,
    "unemployment_rate_15_30": 7.5
  },
  {
    "date": "2016-08-01",
    "year": 2016,
    "month": 8,
    "unemployed_15_24": 305.3,
    "unemployment_rate_15_24": 11.6,
    "unemployed_15_30": 412.9,
    "unemployment_rate_15_30": 6.8
  },
  {
    "date": "2016-09-01",
    "year": 2016,
    "month": 9,
    "unemployed_15_24": 266.3,
    "unemployment_rate_15_24": 10.6,
    "unemployed_15_30": 369.9,
    "unemployment_rate_15_30": 6.4
  },
  {
    "date": "2016-10-01",
    "year": 2016,
    "month": 10,
    "unemployed_15_24": 290.5,
    "unemployment_rate_15_24": 11.4,
    "unemployed_15_30": 399.7,
    "unemployment_rate_15_30": 6.8
  },
  {
    "date": "2016-11-01",
    "year": 2016,
    "month": 11,
    "unemployed_15_24": 253.7,
    "unemployment_rate_15_24": 9.5,
    "unemployed_15_30": 391.2,
    "unemployment_rate_15_30": 6.6
  },
  {
    "date": "2016-12-01",
    "year": 2016,
    "month": 12,
    "unemployed_15_24": 267.4,
    "unemployment_rate_15_24": 10.2,
    "unemployed_15_30": 393.6,
    "unemployment_rate_15_30": 6.6
  },
  {
    "date": "2017-01-01",
    "year": 2017,
    "month": 1,
    "unemployed_15_24": 306.2,
    "unemployment_rate_15_24": 12,
    "unemployed_15_30": 410.6,
    "unemployment_rate_15_30": 7
  },
  {
    "date": "2017-02-01",
    "year": 2017,
    "month": 2,
    "unemployed_15_24": 285.4,
    "unemployment_rate_15_24": 11.1,
    "unemployed_15_30": 413.7,
    "unemployment_rate_15_30": 7
  },
  {
    "date": "2017-03-01",
    "year": 2017,
    "month": 3,
    "unemployed_15_24": 258.9,
    "unemployment_rate_15_24": 10.1,
    "unemployed_15_30": 392.2,
    "unemployment_rate_15_30": 6.6
  },
  {
    "date": "2017-04-01",
    "year": 2017,
    "month": 4,
    "unemployed_15_24": 272.2,
    "unemployment_rate_15_24": 10.8,
    "unemployed_15_30": 414.5,
    "unemployment_rate_15_30": 6.9
  },
  {
    "date": "2017-05-01",
    "year": 2017,
    "month": 5,
    "unemployed_15_24": 320.2,
    "unemployment_rate_15_24": 12.2,
    "unemployed_15_30": 418.8,
    "unemployment_rate_15_30": 7
  },
  {
    "date": "2017-06-01",
    "year": 2017,
    "month": 6,
    "unemployed_15_24": 296.5,
    "unemployment_rate_15_24": 11.4,
    "unemployed_15_30": 420.1,
    "unemployment_rate_15_30": 7
  },
  {
    "date": "2017-07-01",
    "year": 2017,
    "month": 7,
    "unemployed_15_24": 281.1,
    "unemployment_rate_15_24": 11.3,
    "unemployed_15_30": 445.1,
    "unemployment_rate_15_30": 7.6
  },
  {
    "date": "2017-08-01",
    "year": 2017,
    "month": 8,
    "unemployed_15_24": 295.9,
    "unemployment_rate_15_24": 11.6,
    "unemployed_15_30": 423.1,
    "unemployment_rate_15_30": 7.1
  },
  {
    "date": "2017-09-01",
    "year": 2017,
    "month": 9,
    "unemployed_15_24": 267.4,
    "unemployment_rate_15_24": 10.3,
    "unemployed_15_30": 377.5,
    "unemployment_rate_15_30": 6.4
  },
  {
    "date": "2017-10-01",
    "year": 2017,
    "month": 10,
    "unemployed_15_24": 303.6,
    "unemployment_rate_15_24": 11.7,
    "unemployed_15_30": 418.8,
    "unemployment_rate_15_30": 7
  },
  {
    "date": "2017-11-01",
    "year": 2017,
    "month": 11,
    "unemployed_15_24": 314.4,
    "unemployment_rate_15_24": 11.7,
    "unemployed_15_30": 406.7,
    "unemployment_rate_15_30": 6.7
  },
  {
    "date": "2017-12-01",
    "year": 2017,
    "month": 12,
    "unemployed_15_24": 309,
    "unemployment_rate_15_24": 11.7,
    "unemployed_15_30": 404.7,
    "unemployment_rate_15_30": 6.8
  },
  {
    "date": "2018-01-01",
    "year": 2018,
    "month": 1,
    "unemployed_15_24": 328.5,
    "unemployment_rate_15_24": 12.3,
    "unemployed_15_30": 437.6,
    "unemployment_rate_15_30": 7.2
  },
  {
    "date": "2018-02-01",
    "year": 2018,
    "month": 2,
    "unemployed_15_24": 310.9,
    "unemployment_rate_15_24": 11.6,
    "unemployed_15_30": 423,
    "unemployment_rate_15_30": 6.9
  },
  {
    "date": "2018-03-01",
    "year": 2018,
    "month": 3,
    "unemployed_15_24": 306.2,
    "unemployment_rate_15_24": 11.7,
    "unemployed_15_30": 414.4,
    "unemployment_rate_15_30": 6.9
  },
  {
    "date": "2018-04-01",
    "year": 2018,
    "month": 4,
    "unemployed_15_24": 287.9,
    "unemployment_rate_15_24": 10.6,
    "unemployed_15_30": 420.3,
    "unemployment_rate_15_30": 6.8
  },
  {
    "date": "2018-05-01",
    "year": 2018,
    "month": 5,
    "unemployed_15_24": 292.5,
    "unemployment_rate_15_24": 10.6,
    "unemployed_15_30": 391.9,
    "unemployment_rate_15_30": 6.4
  },
  {
    "date": "2018-06-01",
    "year": 2018,
    "month": 6,
    "unemployed_15_24": 284.3,
    "unemployment_rate_15_24": 10.4,
    "unemployed_15_30": 426.9,
    "unemployment_rate_15_30": 6.9
  },
  {
    "date": "2018-07-01",
    "year": 2018,
    "month": 7,
    "unemployed_15_24": 320.6,
    "unemployment_rate_15_24": 11.8,
    "unemployed_15_30": 425.4,
    "unemployment_rate_15_30": 6.9
  },
  {
    "date": "2018-08-01",
    "year": 2018,
    "month": 8,
    "unemployed_15_24": 303.2,
    "unemployment_rate_15_24": 11.5,
    "unemployed_15_30": 407,
    "unemployment_rate_15_30": 6.7
  },
  {
    "date": "2018-09-01",
    "year": 2018,
    "month": 9,
    "unemployed_15_24": 289.5,
    "unemployment_rate_15_24": 10.5,
    "unemployed_15_30": 413.3,
    "unemployment_rate_15_30": 6.8
  },
  {
    "date": "2018-10-01",
    "year": 2018,
    "month": 10,
    "unemployed_15_24": 277.2,
    "unemployment_rate_15_24": 10.1,
    "unemployed_15_30": 429.1,
    "unemployment_rate_15_30": 7
  },
  {
    "date": "2018-11-01",
    "year": 2018,
    "month": 11,
    "unemployed_15_24": 289,
    "unemployment_rate_15_24": 10.5,
    "unemployed_15_30": 415.1,
    "unemployment_rate_15_30": 6.7
  },
  {
    "date": "2018-12-01",
    "year": 2018,
    "month": 12,
    "unemployed_15_24": 328.7,
    "unemployment_rate_15_24": 11.7,
    "unemployed_15_30": 428.8,
    "unemployment_rate_15_30": 6.8
  },
  {
    "date": "2019-01-01",
    "year": 2019,
    "month": 1,
    "unemployed_15_24": 290.1,
    "unemployment_rate_15_24": 10.6,
    "unemployed_15_30": 409.3,
    "unemployment_rate_15_30": 6.7
  },
  {
    "date": "2019-02-01",
    "year": 2019,
    "month": 2,
    "unemployed_15_24": 282.1,
    "unemployment_rate_15_24": 10.5,
    "unemployed_15_30": 424.3,
    "unemployment_rate_15_30": 6.8
  },
  {
    "date": "2019-03-01",
    "year": 2019,
    "month": 3,
    "unemployed_15_24": 266.3,
    "unemployment_rate_15_24": 9.9,
    "unemployed_15_30": 403,
    "unemployment_rate_15_30": 6.6
  },
  {
    "date": "2019-04-01",
    "year": 2019,
    "month": 4,
    "unemployed_15_24": 288.1,
    "unemployment_rate_15_24": 10.3,
    "unemployed_15_30": 430,
    "unemployment_rate_15_30": 6.9
  },
  {
    "date": "2019-05-01",
    "year": 2019,
    "month": 5,
    "unemployed_15_24": 289.3,
    "unemployment_rate_15_24": 10.5,
    "unemployed_15_30": 414.4,
    "unemployment_rate_15_30": 6.7
  },
  {
    "date": "2019-06-01",
    "year": 2019,
    "month": 6,
    "unemployed_15_24": 287,
    "unemployment_rate_15_24": 10.5,
    "unemployed_15_30": 418.5,
    "unemployment_rate_15_30": 6.8
  },
  {
    "date": "2019-07-01",
    "year": 2019,
    "month": 7,
    "unemployed_15_24": 291.3,
    "unemployment_rate_15_24": 10.2,
    "unemployed_15_30": 434.4,
    "unemployment_rate_15_30": 7
  },
  {
    "date": "2019-08-01",
    "year": 2019,
    "month": 8,
    "unemployed_15_24": 297.8,
    "unemployment_rate_15_24": 11.2,
    "unemployed_15_30": 441.2,
    "unemployment_rate_15_30": 7.3
  },
  {
    "date": "2019-09-01",
    "year": 2019,
    "month": 9,
    "unemployed_15_24": 307.1,
    "unemployment_rate_15_24": 11.1,
    "unemployed_15_30": 443.4,
    "unemployment_rate_15_30": 7.2
  },
  {
    "date": "2019-10-01",
    "year": 2019,
    "month": 10,
    "unemployed_15_24": 244.5,
    "unemployment_rate_15_24": 9,
    "unemployed_15_30": 404.8,
    "unemployment_rate_15_30": 6.4
  },
  {
    "date": "2019-11-01",
    "year": 2019,
    "month": 11,
    "unemployed_15_24": 274.2,
    "unemployment_rate_15_24": 9.5,
    "unemployed_15_30": 411.8,
    "unemployment_rate_15_30": 6.5
  },
  {
    "date": "2019-12-01",
    "year": 2019,
    "month": 12,
    "unemployed_15_24": 309.9,
    "unemployment_rate_15_24": 11.2,
    "unemployed_15_30": 412.9,
    "unemployment_rate_15_30": 6.5
  },
  {
    "date": "2020-01-01",
    "year": 2020,
    "month": 1,
    "unemployed_15_24": 268.1,
    "unemployment_rate_15_24": 10,
    "unemployed_15_30": 396.9,
    "unemployment_rate_15_30": 6.4
  },
  {
    "date": "2020-02-01",
    "year": 2020,
    "month": 2,
    "unemployed_15_24": 288,
    "unemployment_rate_15_24": 10.8,
    "unemployed_15_30": 395,
    "unemployment_rate_15_30": 6.4
  },
  {
    "date": "2020-03-01",
    "year": 2020,
    "month": 3,
    "unemployed_15_24": 291.4,
    "unemployment_rate_15_24": 11.3,
    "unemployed_15_30": 470.5,
    "unemployment_rate_15_30": 7.8
  },
  {
    "date": "2020-04-01",
    "year": 2020,
    "month": 4,
    "unemployed_15_24": 324.2,
    "unemployment_rate_15_24": 12.9,
    "unemployed_15_30": 528,
    "unemployment_rate_15_30": 9
  },
  {
    "date": "2020-05-01",
    "year": 2020,
    "month": 5,
    "unemployed_15_24": 362.4,
    "unemployment_rate_15_24": 14.2,
    "unemployed_15_30": 573.7,
    "unemployment_rate_15_30": 10
  },
  {
    "date": "2020-06-01",
    "year": 2020,
    "month": 6,
    "unemployed_15_24": 335.8,
    "unemployment_rate_15_24": 13.1,
    "unemployed_15_30": 581.7,
    "unemployment_rate_15_30": 9.7
  },
  {
    "date": "2020-07-01",
    "year": 2020,
    "month": 7,
    "unemployed_15_24": 313.2,
    "unemployment_rate_15_24": 13.9,
    "unemployed_15_30": 544.5,
    "unemployment_rate_15_30": 9.7
  },
  {
    "date": "2020-08-01",
    "year": 2020,
    "month": 8,
    "unemployed_15_24": 331,
    "unemployment_rate_15_24": 13.7,
    "unemployed_15_30": 502.3,
    "unemployment_rate_15_30": 8.9
  },
  {
    "date": "2020-09-01",
    "year": 2020,
    "month": 9,
    "unemployed_15_24": 325.5,
    "unemployment_rate_15_24": 13,
    "unemployed_15_30": 502.6,
    "unemployment_rate_15_30": 8.5
  },
  {
    "date": "2020-10-01",
    "year": 2020,
    "month": 10,
    "unemployed_15_24": 321.6,
    "unemployment_rate_15_24": 13.4,
    "unemployed_15_30": 513.2,
    "unemployment_rate_15_30": 8.9
  },
  {
    "date": "2020-11-01",
    "year": 2020,
    "month": 11,
    "unemployed_15_24": 344.5,
    "unemployment_rate_15_24": 13,
    "unemployed_15_30": 528.4,
    "unemployment_rate_15_30": 8.8
  },
  {
    "date": "2020-12-01",
    "year": 2020,
    "month": 12,
    "unemployed_15_24": 312.2,
    "unemployment_rate_15_24": 13.2,
    "unemployed_15_30": 497.2,
    "unemployment_rate_15_30": 8.7
  },
  {
    "date": "2021-01-01",
    "year": 2021,
    "month": 1,
    "unemployed_15_24": 295.3,
    "unemployment_rate_15_24": 13.5,
    "unemployed_15_30": 509.2,
    "unemployment_rate_15_30": 9.2
  },
  {
    "date": "2021-02-01",
    "year": 2021,
    "month": 2,
    "unemployed_15_24": 347.6,
    "unemployment_rate_15_24": 13.9,
    "unemployed_15_30": 544.3,
    "unemployment_rate_15_30": 9.2
  },
  {
    "date": "2021-03-01",
    "year": 2021,
    "month": 3,
    "unemployed_15_24": 321.1,
    "unemployment_rate_15_24": 13.4,
    "unemployed_15_30": 537.3,
    "unemployment_rate_15_30": 9.3
  },
  {
    "date": "2021-04-01",
    "year": 2021,
    "month": 4,
    "unemployed_15_24": 310.7,
    "unemployment_rate_15_24": 13.7,
    "unemployed_15_30": 507.3,
    "unemployment_rate_15_30": 8.7
  },
  {
    "date": "2021-05-01",
    "year": 2021,
    "month": 5,
    "unemployed_15_24": 328.1,
    "unemployment_rate_15_24": 13.6,
    "unemployed_15_30": 545.7,
    "unemployment_rate_15_30": 9.2
  },
  {
    "date": "2021-06-01",
    "year": 2021,
    "month": 6,
    "unemployed_15_24": 340.9,
    "unemployment_rate_15_24": 12.7,
    "unemployed_15_30": 565.1,
    "unemployment_rate_15_30": 9.4
  },
  {
    "date": "2021-07-01",
    "year": 2021,
    "month": 7,
    "unemployed_15_24": 344.1,
    "unemployment_rate_15_24": 13.7,
    "unemployed_15_30": 520.6,
    "unemployment_rate_15_30": 8.5
  },
  {
    "date": "2021-08-01",
    "year": 2021,
    "month": 8,
    "unemployed_15_24": 321.1,
    "unemployment_rate_15_24": 13.9,
    "unemployed_15_30": 524.1,
    "unemployment_rate_15_30": 8.8
  },
  {
    "date": "2021-09-01",
    "year": 2021,
    "month": 9,
    "unemployed_15_24": 335.1,
    "unemployment_rate_15_24": 13.9,
    "unemployed_15_30": 507.8,
    "unemployment_rate_15_30": 8.5
  },
  {
    "date": "2021-10-01",
    "year": 2021,
    "month": 10,
    "unemployed_15_24": 358.8,
    "unemployment_rate_15_24": 13.9,
    "unemployed_15_30": 508.4,
    "unemployment_rate_15_30": 8.1
  },
  {
    "date": "2021-11-01",
    "year": 2021,
    "month": 11,
    "unemployed_15_24": 350.9,
    "unemployment_rate_15_24": 13.7,
    "unemployed_15_30": 517.9,
    "unemployment_rate_15_30": 8.2
  },
  {
    "date": "2021-12-01",
    "year": 2021,
    "month": 12,
    "unemployed_15_24": 367.7,
    "unemployment_rate_15_24": 13.7,
    "unemployed_15_30": 533.8,
    "unemployment_rate_15_30": 8.5
  },
  {
    "date": "2022-01-01",
    "year": 2022,
    "month": 1,
    "unemployed_15_24": 364.5,
    "unemployment_rate_15_24": 13.2,
    "unemployed_15_30": 521.8,
    "unemployment_rate_15_30": 8.3
  },
  {
    "date": "2022-02-01",
    "year": 2022,
    "month": 2,
    "unemployed_15_24": 356.9,
    "unemployment_rate_15_24": 13,
    "unemployed_15_30": 513.7,
    "unemployment_rate_15_30": 8.1
  },
  {
    "date": "2022-03-01",
    "year": 2022,
    "month": 3,
    "unemployed_15_24": 361,
    "unemployment_rate_15_24": 13.1,
    "unemployed_15_30": 502.4,
    "unemployment_rate_15_30": 8
  },
  {
    "date": "2022-04-01",
    "year": 2022,
    "month": 4,
    "unemployed_15_24": 357.2,
    "unemployment_rate_15_24": 12.8,
    "unemployed_15_30": 501.2,
    "unemployment_rate_15_30": 7.7
  },
  {
    "date": "2022-05-01",
    "year": 2022,
    "month": 5,
    "unemployed_15_24": 341.4,
    "unemployment_rate_15_24": 12.5,
    "unemployed_15_30": 475.7,
    "unemployment_rate_15_30": 7.4
  },
  {
    "date": "2022-06-01",
    "year": 2022,
    "month": 6,
    "unemployed_15_24": 343.9,
    "unemployment_rate_15_24": 12.2,
    "unemployed_15_30": 474.7,
    "unemployment_rate_15_30": 7.4
  },
  {
    "date": "2022-07-01",
    "year": 2022,
    "month": 7,
    "unemployed_15_24": 336.2,
    "unemployment_rate_15_24": 12.1,
    "unemployed_15_30": 476.5,
    "unemployment_rate_15_30": 7.4
  },
  {
    "date": "2022-08-01",
    "year": 2022,
    "month": 8,
    "unemployed_15_24": 337.6,
    "unemployment_rate_15_24": 12.1,
    "unemployed_15_30": 467.5,
    "unemployment_rate_15_30": 7.1
  },
  {
    "date": "2022-09-01",
    "year": 2022,
    "month": 9,
    "unemployed_15_24": 339.1,
    "unemployment_rate_15_24": 12.1,
    "unemployed_15_30": 460.4,
    "unemployment_rate_15_30": 7.1
  },
  {
    "date": "2022-10-01",
    "year": 2022,
    "month": 10,
    "unemployed_15_24": 337.2,
    "unemployment_rate_15_24": 12.1,
    "unemployed_15_30": 476.9,
    "unemployment_rate_15_30": 7.4
  },
  {
    "date": "2022-11-01",
    "year": 2022,
    "month": 11,
    "unemployed_15_24": 329.3,
    "unemployment_rate_15_24": 11.9,
    "unemployed_15_30": 453.1,
    "unemployment_rate_15_30": 7
  },
  {
    "date": "2022-12-01",
    "year": 2022,
    "month": 12,
    "unemployed_15_24": 331,
    "unemployment_rate_15_24": 11.8,
    "unemployed_15_30": 444.5,
    "unemployment_rate_15_30": 6.9
  },
  {
    "date": "2023-01-01",
    "year": 2023,
    "month": 1,
    "unemployed_15_24": 328.8,
    "unemployment_rate_15_24": 11.5,
    "unemployed_15_30": 449.7,
    "unemployment_rate_15_30": 7
  },
  {
    "date": "2023-02-01",
    "year": 2023,
    "month": 2,
    "unemployed_15_24": 320.8,
    "unemployment_rate_15_24": 11.3,
    "unemployed_15_30": 450.2,
    "unemployment_rate_15_30": 7
  },
  {
    "date": "2023-03-01",
    "year": 2023,
    "month": 3,
    "unemployed_15_24": 317.3,
    "unemployment_rate_15_24": 11.2,
    "unemployed_15_30": 454.9,
    "unemployment_rate_15_30": 7.1
  },
  {
    "date": "2023-04-01",
    "year": 2023,
    "month": 4,
    "unemployed_15_24": 315.6,
    "unemployment_rate_15_24": 11.1,
    "unemployed_15_30": 441,
    "unemployment_rate_15_30": 6.7
  },
  {
    "date": "2023-05-01",
    "year": 2023,
    "month": 5,
    "unemployed_15_24": 313,
    "unemployment_rate_15_24": 11,
    "unemployed_15_30": 448.6,
    "unemployment_rate_15_30": 7
  },
  {
    "date": "2023-06-01",
    "year": 2023,
    "month": 6,
    "unemployed_15_24": 312.4,
    "unemployment_rate_15_24": 11,
    "unemployed_15_30": 444.8,
    "unemployment_rate_15_30": 6.9
  },
  {
    "date": "2023-07-01",
    "year": 2023,
    "month": 7,
    "unemployed_15_24": 311.2,
    "unemployment_rate_15_24": 10.9,
    "unemployed_15_30": 444.8,
    "unemployment_rate_15_30": 6.8
  },
  {
    "date": "2023-08-01",
    "year": 2023,
    "month": 8,
    "unemployed_15_24": 309.2,
    "unemployment_rate_15_24": 10.8,
    "unemployed_15_30": 439.6,
    "unemployment_rate_15_30": 6.8
  },
  {
    "date": "2023-09-01",
    "year": 2023,
    "month": 9,
    "unemployed_15_24": 310.1,
    "unemployment_rate_15_24": 10.6,
    "unemployed_15_30": 440,
    "unemployment_rate_15_30": 6.7
  },
  {
    "date": "2023-10-01",
    "year": 2023,
    "month": 10,
    "unemployed_15_24": 313.3,
    "unemployment_rate_15_24": 10.7,
    "unemployed_15_30": 439.6,
    "unemployment_rate_15_30": 6.6
  },
  {
    "date": "2023-11-01",
    "year": 2023,
    "month": 11,
    "unemployed_15_24": 308.5,
    "unemployment_rate_15_24": 10.6,
    "unemployed_15_30": 432,
    "unemployment_rate_15_30": 6.5
  },
  {
    "date": "2023-12-01",
    "year": 2023,
    "month": 12,
    "unemployed_15_24": 307.2,
    "unemployment_rate_15_24": 10.6,
    "unemployed_15_30": 432.1,
    "unemployment_rate_15_30": 6.4
  },
  {
    "date": "2024-01-01",
    "year": 2024,
    "month": 1,
    "unemployed_15_24": 299.1,
    "unemployment_rate_15_24": 10.7,
    "unemployed_15_30": 422.2,
    "unemployment_rate_15_30": 6.9
  },
  {
    "date": "2024-02-01",
    "year": 2024,
    "month": 2,
    "unemployed_15_24": 295.7,
    "unemployment_rate_15_24": 10.6,
    "unemployed_15_30": 420.1,
    "unemployment_rate_15_30": 6.9
  },
  {
    "date": "2024-03-01",
    "year": 2024,
    "month": 3,
    "unemployed_15_24": 296.9,
    "unemployment_rate_15_24": 10.6,
    "unemployed_15_30": 420.3,
    "unemployment_rate_15_30": 6.9
  },
  {
    "date": "2024-04-01",
    "year": 2024,
    "month": 4,
    "unemployed_15_24": 293.6,
    "unemployment_rate_15_24": 10.5,
    "unemployed_15_30": 416.6,
    "unemployment_rate_15_30": 6.8
  },
  {
    "date": "2024-05-01",
    "year": 2024,
    "month": 5,
    "unemployed_15_24": 295.6,
    "unemployment_rate_15_24": 10.5,
    "unemployed_15_30": 412,
    "unemployment_rate_15_30": 6.7
  },
  {
    "date": "2024-06-01",
    "year": 2024,
    "month": 6,
    "unemployed_15_24": 293.5,
    "unemployment_rate_15_24": 10.4,
    "unemployed_15_30": 409,
    "unemployment_rate_15_30": 6.7
  },
  {
    "date": "2024-07-01",
    "year": 2024,
    "month": 7,
    "unemployed_15_24": 294.6,
    "unemployment_rate_15_24": 10.4,
    "unemployed_15_30": 404.3,
    "unemployment_rate_15_30": 6.6
  },
  {
    "date": "2024-08-01",
    "year": 2024,
    "month": 8,
    "unemployed_15_24": 294.8,
    "unemployment_rate_15_24": 10.4,
    "unemployed_15_30": 404.7,
    "unemployment_rate_15_30": 6.6
  },
  {
    "date": "2024-09-01",
    "year": 2024,
    "month": 9,
    "unemployed_15_24": 295.6,
    "unemployment_rate_15_24": 10.4,
    "unemployed_15_30": 407.6,
    "unemployment_rate_15_30": 6.4
  },
  {
    "date": "2024-10-01",
    "year": 2024,
    "month": 10,
    "unemployed_15_24": 300.6,
    "unemployment_rate_15_24": 10.5,
    "unemployed_15_30": 402.8,
    "unemployment_rate_15_30": 6.3
  },
  {
    "date": "2024-11-01",
    "year": 2024,
    "month": 11,
    "unemployed_15_24": 300,
    "unemployment_rate_15_24": 10.4,
    "unemployed_15_30": 401.8,
    "unemployment_rate_15_30": 6.3
  },
  {
    "date": "2024-12-01",
    "year": 2024,
    "month": 12,
    "unemployed_15_24": 301.4,
    "unemployment_rate_15_24": 10.4,
    "unemployed_15_30": 400.7,
    "unemployment_rate_15_30": 6.3
  },
  {
    "date": "2025-01-01",
    "year": 2025,
    "month": 1,
    "unemployed_15_24": 299.3,
    "unemployment_rate_15_24": 10.3,
    "unemployed_15_30": 402.4,
    "unemployment_rate_15_30": 6.3
  },
  {
    "date": "2025-02-01",
    "year": 2025,
    "month": 2,
    "unemployed_15_24": 298.9,
    "unemployment_rate_15_24": 10.3,
    "unemployed_15_30": 401.6,
    "unemployment_rate_15_30": 6.3
  },
  {
    "date": "2025-03-01",
    "year": 2025,
    "month": 3,
    "unemployed_15_24": 299.7,
    "unemployment_rate_15_24": 10.3,
    "unemployed_15_30": 399.4,
    "unemployment_rate_15_30": 6.3
  },
  {
    "date": "2025-04-01",
    "year": 2025,
    "month": 4,
    "unemployed_15_24": 298.3,
    "unemployment_rate_15_24": 10.3,
    "unemployed_15_30": 400.6,
    "unemployment_rate_15_30": 6.2
  },
  {
    "date": "2025-05-01",
    "year": 2025,
    "month": 5,
    "unemployed_15_24": 297.7,
    "unemployment_rate_15_24": 10.2,
    "unemployed_15_30": 399,
    "unemployment_rate_15_30": 6.2
  },
  {
    "date": "2025-06-01",
    "year": 2025,
    "month": 6,
    "unemployed_15_24": 297.5,
    "unemployment_rate_15_24": 10.2,
    "unemployed_15_30": 396.8,
    "unemployment_rate_15_30": 6.2
  },
  {
    "date": "2025-07-01",
    "year": 2025,
    "month": 7,
    "unemployed_15_24": 298.9,
    "unemployment_rate_15_24": 10.2,
    "unemployed_15_30": 399,
    "unemployment_rate_15_30": 6.2
  },
  {
    "date": "2025-08-01",
    "year": 2025,
    "month": 8,
    "unemployed_15_24": 298,
    "unemployment_rate_15_24": 10.2,
    "unemployed_15_30": 398.7,
    "unemployment_rate_15_30": 6.2
  },
  {
    "date": "2025-09-01",
    "year": 2025,
    "month": 9,
    "unemployed_15_24": 296.9,
    "unemployment_rate_15_24": 10.1,
    "unemployed_15_30": 398.1,
    "unemployment_rate_15_30": 6.2
  },
  {
    "date": "2025-10-01",
    "year": 2025,
    "month": 10,
    "unemployed_15_24": 297.6,
    "unemployment_rate_15_24": 10.1,
    "unemployed_15_30": 398.5,
    "unemployment_rate_15_30": 6.1
  },
  {
    "date": "2025-11-01",
    "year": 2025,
    "month": 11,
    "unemployed_15_24": 297.9,
    "unemployment_rate_15_24": 10.1,
    "unemployed_15_30": 398,
    "unemployment_rate_15_30": 6.1
  },
  {
    "date": "2025-12-01",
    "year": 2025,
    "month": 12,
    "unemployed_15_24": 298.7,
    "unemployment_rate_15_24": 10.1,
    "unemployed_15_30": 396.9,
    "unemployment_rate_15_30": 6.1
  }
]